immute.py
immute-0.3.3.dist-info/LICENSE
immute-0.3.3.dist-info/WHEEL
immute-0.3.3.dist-info/METADATA
immute-0.3.3.dist-info/RECORD
