Metadata-Version: 2.1
Name: immute
Version: 0.3.3
Summary: Create immutable python classes
Home-page: https://github.com/fitzypop/immute
License: MIT
Author: fitzypop
Author-email: fitzypop@pm.me
Requires-Python: >=3.7,<4.0
Classifier: License :: OSI Approved :: MIT License
Classifier: Programming Language :: Python :: 3
Classifier: Programming Language :: Python :: 3.10
Classifier: Programming Language :: Python :: 3.7
Classifier: Programming Language :: Python :: 3.8
Classifier: Programming Language :: Python :: 3.9
Project-URL: Repository, https://github.com/fitzypop/immute
